health_check/__init__.py
health_check/_version.py
health_check/backends.py
health_check/conf.py
health_check/deprecation.py
health_check/exceptions.py
health_check/mixins.py
health_check/plugins.py
health_check/urls.py
health_check/views.py
health_check/cache/__init__.py
health_check/cache/apps.py
health_check/cache/backends.py
health_check/contrib/__init__.py
health_check/contrib/celery/__init__.py
health_check/contrib/celery/apps.py
health_check/contrib/celery/backends.py
health_check/contrib/celery/tasks.py
health_check/contrib/celery_ping/__init__.py
health_check/contrib/celery_ping/apps.py
health_check/contrib/celery_ping/backends.py
health_check/contrib/db_heartbeat/__init__.py
health_check/contrib/db_heartbeat/apps.py
health_check/contrib/db_heartbeat/backends.py
health_check/contrib/mail/__init__.py
health_check/contrib/mail/apps.py
health_check/contrib/mail/backends.py
health_check/contrib/migrations/__init__.py
health_check/contrib/migrations/apps.py
health_check/contrib/migrations/backends.py
health_check/contrib/psutil/__init__.py
health_check/contrib/psutil/apps.py
health_check/contrib/psutil/backends.py
health_check/contrib/rabbitmq/__init__.py
health_check/contrib/rabbitmq/apps.py
health_check/contrib/rabbitmq/backends.py
health_check/contrib/redis/__init__.py
health_check/contrib/redis/apps.py
health_check/contrib/redis/backends.py
health_check/contrib/s3boto3_storage/__init__.py
health_check/contrib/s3boto3_storage/apps.py
health_check/contrib/s3boto3_storage/backends.py
health_check/contrib/s3boto_storage/__init__.py
health_check/contrib/s3boto_storage/apps.py
health_check/contrib/s3boto_storage/backends.py
health_check/db/__init__.py
health_check/db/apps.py
health_check/db/backends.py
health_check/db/models.py
health_check/db/migrations/0001_initial.py
health_check/db/migrations/0002_alter_testmodel_options.py
health_check/db/migrations/__init__.py
health_check/management/__init__.py
health_check/management/commands/__init__.py
django_health_check-3.21.0.dist-info/licenses/LICENSE
django_health_check-3.21.0.dist-info/WHEEL
django_health_check-3.21.0.dist-info/METADATA
django_health_check-3.21.0.dist-info/RECORD
