Metadata-Version: 2.4
Name: django-health-check
Version: 3.21.0
Summary: Monitor the health of your Django app and its connected services.
Keywords: django,postgresql
Author-email: Kristian Ollegaard <kristian@oellegaard.com>, Johannes Maron <johannes@maron.family>
Requires-Python: >=3.10
Classifier: Development Status :: 5 - Production/Stable
Classifier: Framework :: Django
Classifier: Framework :: Django :: 4.2
Classifier: Framework :: Django :: 5.2
Classifier: Framework :: Django :: 6.0
Classifier: Intended Audience :: Developers
Classifier: License :: OSI Approved :: MIT License
Classifier: Operating System :: OS Independent
Classifier: Programming Language :: Python
Classifier: Programming Language :: Python :: 3
Classifier: Programming Language :: Python :: 3 :: Only
Classifier: Programming Language :: Python :: 3.10
Classifier: Programming Language :: Python :: 3.11
Classifier: Programming Language :: Python :: 3.12
Classifier: Programming Language :: Python :: 3.13
Classifier: Programming Language :: Python :: 3.14
Classifier: Topic :: Software Development :: Quality Assurance
Classifier: Topic :: System :: Logging
Classifier: Topic :: System :: Monitoring
Classifier: Topic :: Utilities
License-File: LICENSE
Requires-Dist: Django>=4.2
Requires-Dist: psutil
Requires-Dist: celery>=5.0.0 ; extra == "celery"
Requires-Dist: kombu>=5.0.0 ; extra == "rabbitmq"
Requires-Dist: redis>=3.0.0 ; extra == "redis"
Project-URL: Changelog, https://github.com/codingjoe/django-health-check/releases
Project-URL: Documentation, https://codingjoe.dev/django-health-check/
Project-URL: Homepage, https://codingjoe.dev/django-health-check/
Project-URL: Issues, https://github.com/codingjoe/django-health-check/issues
Project-URL: Releasenotes, https://github.com/codingjoe/django-health-check/releases/latest
Project-URL: Source, https://github.com/codingjoe/django-health-check
Provides-Extra: celery
Provides-Extra: rabbitmq
Provides-Extra: redis
